randrythm/__init__.py
randrythm/randryth.py
randrythm-1.1.0.dist-info/LICENSE
randrythm-1.1.0.dist-info/METADATA
randrythm-1.1.0.dist-info/WHEEL
randrythm-1.1.0.dist-info/top_level.txt
randrythm-1.1.0.dist-info/RECORD
