Metadata-Version: 2.1
Name: randrythm
Version: 1.1.0
Author: Torrez
Requires-Python: >=3.10
License-File: LICENSE
